sonos_lastfm/__init__.py
sonos_lastfm/__main__.py
sonos_lastfm/cli.py
sonos_lastfm/config.py
sonos_lastfm/sonos_lastfm.py
sonos_lastfm/utils.py
sonos_lastfm-0.1.7.dist-info/METADATA
sonos_lastfm-0.1.7.dist-info/WHEEL
sonos_lastfm-0.1.7.dist-info/entry_points.txt
sonos_lastfm-0.1.7.dist-info/licenses/LICENSE
sonos_lastfm-0.1.7.dist-info/RECORD
