Metadata-Version: 2.4
Name: sonos-lastfm
Version: 0.1.7
Summary: Automatically scrobble music playing on your Sonos speakers to Last.fm
Project-URL: Homepage, https://github.com/denya/sonos-lastfm
Project-URL: Issues, https://github.com/denya/sonos-lastfm/issues
Author-email: Denis Moskalets <denya.msk@gmail.com>
License: MIT
License-File: LICENSE
Keywords: lastfm,music,scrobbler,sonos
Classifier: Development Status :: 4 - Beta
Classifier: Intended Audience :: End Users/Desktop
Classifier: License :: OSI Approved :: MIT License
Classifier: Programming Language :: Python :: 3
Classifier: Programming Language :: Python :: 3.11
Classifier: Programming Language :: Python :: 3.12
Classifier: Topic :: Multimedia :: Sound/Audio
Requires-Python: >=3.11
Requires-Dist: keyring>=24.3.0
Requires-Dist: pylast>=5.1.0
Requires-Dist: python-dotenv>=1.0.0
Requires-Dist: rich>=13.7.0
Requires-Dist: soco>=0.27.0
Requires-Dist: typer>=0.9.0
